{
	"name": "MagicUser Space Night",
	"colors": {
		"titleBar.activeForeground": "#d3d3d388",
		"titleBar.inactiveForeground": "#d3d3d388",
		"activityBar.activeBorder": "#00478d",
		"activityBar.background": "#181818",
		"activityBar.foreground": "#0072d3",
		"activityBar.inactiveForeground": "#cfcfcf48",
		"activityBarBadge.background": "#00478d",
		"activityBarBadge.foreground": "#d8d8d8",
		"badge.background": "#00478d",
		"badge.foreground": "#ccc",
		"debugToolBar.background": "#480048",
		"dropdown.background": "#282828",
		"dropdown.foreground": "#f1f1f1",
		"editor.background": "#101010",
		"editor.selectionHighlightBackground": "#f100f153",
		"editor.findMatchBackground": "#00000088",
		"editor.findMatchBorder": "#f100f1",
		"editor.findMatchHighlightBackground": "#f100f153",
		"editor.foreground": "#d8d8d8c8",
		"editor.lineHighlightBorder": "#007fff20",
		"editor.selectionBackground": "#0033a388",
		"editor.wordHighlightBackground": "#d8d8d800",
		"editor.wordHighlightBorder": "#00ffff48",
		"editor.wordHighlightStrongBackground": "#f100f128",
		"editor.wordHighlightStrongBorder": "#f100f188",
		"editorBracketHighlight.unexpectedBracket.foreground": "#ff1212",
		"editorBracketMatch.background": "#d372ff48",
		"editorBracketMatch.border": "#d372ff",
		"editorCursor.background": "#000",
		"editorCursor.foreground": "#0072d3",
		"editorGroup.border": "#48487f",
		"editorGroup.dropBackground": "#2f4878a3",
		"editorGroupHeader.border": "#10101000",
		"editorGroupHeader.noTabsBackground": "#101010",
		"editorGroupHeader.tabsBackground": "#101010",
		"editorHoverWidget.background": "#101010",
		"editorHoverWidget.border": "#181818",
		"editorHoverWidget.statusBarBackground": "#484848",
		"editorIndentGuide.activeBackground": "#d373ff88",
		"editorIndentGuide.background": "#82828218",
		"editorLineNumber.activeForeground": "#d3d3d353",
		"editorLineNumber.foreground": "#d3d3d328",
		"editorSuggestWidget.background": "#080808",
		"editorSuggestWidget.border": "#101010",
		"editorSuggestWidget.focusHighlightForeground": "#007fff",
		"editorWhitespace.foreground": "#a3a3a3",
		"editorWidget.background": "#101010",
		"errorForeground": "#ff2222",
		"focusBorder": "#007fff88",
		"input.background": "#282828",
		"input.border": "#d8d8d872",
		"input.foreground": "#d8d8d8",
		"list.activeSelectionBackground": "#002248",
		"list.activeSelectionForeground": "#d8d8d8",
		"list.highlightForeground": "#007fff",
		"list.hoverBackground": "#d8d8d820",
		"list.inactiveSelectionBackground": "#181818",
		"menu.background": "#181818",
		"menu.foreground": "#d3d3d3",
		"menu.selectionBackground": "#002248",
		"menu.separatorBackground": "#35353588",
		"menubar.selectionBackground": "#002248",
		"minimap.selectionHighlight": "#003788",
		"peekViewResult.background": "#001c40",
		"pickerGroup.foreground": "#bcdbff",
		"ports.iconRunningProcessForeground": "#bcdbff",
		"profileBadge.background": "#000",
		"profileBadge.foreground": "#00478d",
		"progressBar.background": "#bbdaffcc",
		"quickInputList.focusBackground": "#002248",
		"sideBar.background": "#101010",
		"sideBarSectionHeader.background": "#101010",
		"statusBar.foreground": "#d3d3d3",
		"statusBar.background": "#181818",
		"statusBar.debuggingBackground": "#480048",
		"statusBar.noFolderBackground": "#181818",
		"statusBarItem.remoteBackground": "#007fff",
		"statusBarItem.remoteForeground": "#d8d8d8",
		"tab.activeForeground": "#cfcfcf",
		"tab.activeBorderTop": "#007fff",
		"tab.inactiveBackground": "#101010",
		"tab.lastPinnedBorder": "#007acf88",
		"terminal.ansiBlack": "#111111",
		"terminal.ansiBlue": "#0000ff",
		"terminal.ansiBrightBlack": "#333333",
		"terminal.ansiBrightBlue": "#00a3f1",
		"terminal.ansiBrightCyan": "#48f1f1",
		"terminal.ansiBrightGreen": "#48f148",
		"terminal.ansiBrightMagenta": "#f148f1",
		"terminal.ansiBrightRed": "#f14848",
		"terminal.ansiBrightWhite": "#d8d8d8",
		"terminal.ansiBrightYellow": "#ffff48",
		"terminal.ansiCyan": "#00ffff",
		"terminal.ansiGreen": "#00ff00",
		"terminal.ansiMagenta": "#ff00ff",
		"terminal.ansiRed": "#ff4848",
		"terminal.ansiWhite": "#ffffff",
		"terminal.ansiYellow": "#ffff00",
		"terminal.background": "#000000",
		"terminalCursor.background": "#000000",
		"terminalCursor.foreground": "#0072d3",
		"titleBar.activeBackground": "#181818",
		"titleBar.inactiveBackground": "#181818",
		"widget.border": "#181818",
		"button.background": "#00478d",
		"button.foreground": "#d8d8d8",
		"charts.blue": "#007fff",
		"charts.foreground": "#cccccc",
		"charts.green": "#82d388",
		"charts.lines": "#cccccc88",
		"charts.orange": "#d38818",
		"charts.purple": "#b180d3",
		"charts.red": "#f14848",
		"charts.yellow": "#cba700",
		"checkbox.background": "#282828",
		"checkbox.border": "#007fff",
		"checkbox.foreground": "#f1f1f1",
		"checkbox.selectBackground": "#282828",
		"checkbox.selectBorder": "#007fff",
		"editorBracketHighlight.foreground1": "#d372ffc8",
		"editorBracketHighlight.foreground2": "#18a3ffc8",
		"editorBracketHighlight.foreground3": "#ffd700c8",
		"editorBracketHighlight.foreground4": "#d372ffc8",
		"editorBracketHighlight.foreground5": "#18a3ffc8",
		"editorBracketHighlight.foreground6": "#ffd700c8",
		"searchEditor.findMatchBorder": "#ff00ff",
		"searchEditor.findMatchBackground": "#00ffff88",
		"minimap.findMatchHighlight": "#d372ff",
		"editorGutter.addedBackground": "#18c350",
		"editorGutter.deletedBackground": "#c30028",
		"editorGutter.modifiedBackground": "#b9b52f",
		"list.errorForeground": "#c30028",
		"list.warningForeground": "#f15353",
		"gitDecoration.modifiedResourceForeground": "#b9b52f",
		"gitDecoration.untrackedResourceForeground": "#c37f7f",
		"gitDecoration.addedResourceForeground": "#27c35f",
		"gitDecoration.conflictingResourceForeground": "#ff53b3",
		"gitDecoration.deletedResourceForeground": "#d31f1f",
		"gitDecoration.ignoredResourceForeground": "#ccc",
		"gitDecoration.renamedResourceForeground": "#b9b52f",
		"gitDecoration.stageDeletedResourceForeground": "#f30000",
		"gitDecoration.submoduleResourceForeground": "#f100f1",
		"gitDecoration.stageModifiedResourceForeground": "#4fbf00"
	},
	"tokenColors": [
		{
			"scope": [
				"meta.embedded",
				"source.groovy.embedded",
				"meta.jsx.children",
				"string meta.image.inline.markdown"
			],
			"settings": {
				"foreground": "#d8d8d8c8"
			}
		},
		{
			"scope": "comment",
			"settings": {
				"foreground": "#787878c8",
				"fontStyle": "italic"
			}
		},
		{
			"scope": "keyword.operator.class, constant.other, source.php.embedded.line",
			"settings": {
				"foreground": "#d8d8d8c8",
				"fontStyle": ""
			}
		},
		{
			"scope": "support.other.variable, string.other.link, string.regexp, entity.name.tag, meta.tag, declaration.tag, markup.deleted.git_gutter",
			"settings": {
				"foreground": "#d372ffc8"
			}
		},
		{
			"scope": "constant.numeric, constant.language, support.constant, constant.character, punctuation.section.embedded, keyword.other.unit,constant.language.python",
			"settings": {
				"foreground": "#ffa300c8",
				"fontStyle": ""
			}
		},
		{
			"scope": "entity.name.class, entity.name.type, entity.name.namespace, entity.name.scope-resolution, support.type, support.class",
			"settings": {
				"foreground": "#ff8f00c8",
				"fontStyle": ""
			}
		},
		{
			"scope": "entity.other.inherited-class.python",
			"settings": {
				"foreground": "#ff8f00c8",
				"fontStyle": "italic"
			}
		},
		{
			"scope": "constant.other.symbol, markup.inserted.git_gutter",
			"settings": {
				"foreground": "#c3F1A8c8",
				"fontStyle": ""
			}
		},
		{
			"scope": "constant.other.color",
			"settings": {
				"foreground": "#99FFFFc8"
			}
		},
		{
			"scope": "entity.name.function, meta.function-call, support.function, keyword.other.special-method, meta.block-level, markup.changed.git_gutter",
			"settings": {
				"foreground": "#B3D3FFc8",
				"fontStyle": ""
			}
		},
		{
			"scope": "keyword, storage, storage.type, entity.name.tag.css, keyword.other.special-method.dockerfile",
			"settings": {
				"foreground": "#D372FFc8",
				"fontStyle": ""
			}
		},
		{
			"scope": "invalid",
			"settings": {
				"foreground": "#ff4848",
				"fontStyle": ""
			}
		},
		{
			"scope": "invalid.deprecated",
			"settings": {
				"foreground": "#ff48c8",
				"fontStyle": "bold underline"
			}
		},
		{
			"scope": "markup.inserted.diff, markup.deleted.diff, meta.diff.header.to-file, meta.diff.header.from-file",
			"settings": {
				"foreground": "#d8d8d8c8"
			}
		},
		{
			"scope": "markup.inserted.diff, meta.diff.header.to-file",
			"settings": {
				"foreground": "#72c800"
			}
		},
		{
			"scope": "markup.deleted.diff, meta.diff.header.from-file",
			"settings": {
				"foreground": "#C82828"
			}
		},
		{
			"scope": "meta.diff.header.from-file, meta.diff.header.to-file",
			"settings": {
				"foreground": "#4271AE"
			}
		},
		{
			"scope": "meta.diff.range",
			"settings": {
				"foreground": "#3E999F",
				"fontStyle": "italic"
			}
		},
		{
			"scope": "markup.bold",
			"settings": {
				"fontStyle": "bold"
			}
		},
		{
			"scope": "markup.italic",
			"settings": {
				"fontStyle": "italic"
			}
		},
		{
			"scope": "markup.strikethrough",
			"settings": {
				"fontStyle": "strikethrough"
			}
		},
		{
			"scope": "markup.inline.raw",
			"settings": {
				"foreground": "#FF9DA4c8",
				"fontStyle": ""
			}
		},
		{
			"scope": "markup.heading",
			"settings": {
				"fontStyle": "bold"
			}
		},
		{
			"scope": "token.info-token",
			"settings": {
				"foreground": "#7299f1c8"
			}
		},
		{
			"scope": "token.warn-token",
			"settings": {
				"foreground": "#f7c33fc8"
			}
		},
		{
			"scope": "token.error-token",
			"settings": {
				"foreground": "#F14848c8"
			}
		},
		{
			"scope": "token.debug-token",
			"settings": {
				"foreground": "#c365f1c8"
			}
		},
		{
			"scope": "string",
			"settings": {
				"foreground": "#48d8ffc8"
			}
		},
		{
			"scope": "meta.embedded.assembly",
			"settings": {
				"foreground": "#00F1F1c8"
			}
		},
		{
			"scope": "keyword.control",
			"settings": {
				"foreground": "#D372FFc8"
			}
		},
		{
			"scope": "storage",
			"settings": {
				"foreground": "#D372FFc8"
			}
		},
		{
			"scope": "storage.type",
			"settings": {
				"foreground": "#D372FFc8"
			}
		},
		{
			"scope": "entity.name.class",
			"settings": {
				"foreground": "#FFA300c8"
			}
		},
		{
			"scope": "support.type",
			"settings": {
				"foreground": "#FFA300c8"
			}
		},
		{
			"scope": "entity.name.function, support.function",
			"settings": {
				"foreground": "#bcffbcc8"
			}
		},
		{
			"scope": "variable, entity.name.variable",
			"settings": {
				"foreground": "#d8d8d8c8"
			}
		},
		{
			"scope": "punctuation.definition.tag, entity.name.tag.html",
			"settings": {
				"foreground": "#d372ffc8"
			}
		},
		{
			"scope": "token.info-token",
			"settings": {
				"foreground": "#7299F1c8"
			}
		},
		{
			"scope": "token.warn-token",
			"settings": {
				"foreground": "#FFD348c8"
			}
		},
		{
			"scope": "token.error-token",
			"settings": {
				"foreground": "#FF4848c8"
			}
		},
		{
			"scope": "token.debug-token",
			"settings": {
				"foreground": "#B365FFc8"
			}
		},
		{
			"scope": "keyword.operator,punctuation.separator, punctuation.terminator, punctuation.section.class.begin.python, punctuation.section.function.begin.python,keyword.operator.assignment.python",
			"settings": {
				"foreground": "#d372ffc8"
			}
		},
		{
			"scope": "entity.name.namespace, entity.name.type.namespace.cs",
			"settings": {
				"foreground": "#00f1f1c8"
			}
		},
		{
			"scope": "support.variable.magic.python",
			"settings": {
				"foreground": "#ff00b3c8",
				"fontStyle": ""
			}
		},
		{
			"scope": "variable,variable.parameter, meta.function-call.arguments.python, meta.var.expr.js",
			"settings": {
				"foreground": "#d8d8d8c8",
				"fontStyle": ""
			}
		},
		{
			"scope": "constant.language",
			"settings": {
				"foreground": "#FF8800c8"
			}
		},
		{
			"scope": "entity",
			"settings": {
				"foreground": "#DB00BEc8"
			}
		},
		{
			"scope": "variable.language.special.self.python, variable.parameter.function.language.special.self.python, variable.language.this.js",
			"settings": {
				"foreground": "#0088ffc8",
				"fontStyle": ""
			}
		},
		{
			"scope": "variable.other.constant.js.jsx,variable.parameter.js.jsx,variable.other.object.js.jsx, meta.definition.variable.js.jsx",
			"settings": {
				"foreground": "#d8d8d8c8"
			}
		},
		{
			"scope": "support.class.component.js.jsx",
			"settings": {
				"foreground": "#ffa420c8",
			}
		},
		{
			"scope": "punctuation.definition.block.js.jsx, entity.name.tag.js.jsx, meta.tag.without-attributes.js.jsx",
			"settings": {
				"foreground": "#ff88ffc8",
			}
		},
		{
			"scope": "variable.other.property.js, meta.object-literal.key.js",
			"settings": {
				"foreground": "#a3c3ffc8",
				"fontStyle": ""
			}
		},
		{
			"scope": "meta.attribute.python, meta.indexed-name.python",
			"settings": {
				"foreground": "#d8d8d8c8"
			}
		},
		{
			"scope": "entity.name.tag, punctuation.separator.key-value.html",
			"settings": {
				"foreground": "#D372FFc8"
			}
		},
		{
			"scope": "support.variable",
			"settings": {
				"foreground": "#00B3B3c8",
				"fontStyle": "italic"
			}
		},
		{
			"scope": "markup.heading,punctuation.definition.link.description.begin.markdown,punctuation.definition.link.description.end.markdown, punctuation.definition.quote.begin.markdown,punctuation.definition.link.title.begin.markdown,punctuation.definition.link.title.end.markdown, punctuation.definition.metadata.markdown,punctuation.definition.list.begin.markdown, punctuation.accessor.cs",
			"settings": {
				"foreground": "#d372ffc8"
			}
		},
		{
			"scope": "markup.list",
			"settings": {
				"foreground": "#d8d8d8c8"
			}
		},
		{
			"scope": "markup.quote",
			"settings": {
				"foreground": "#d8d8d8c8"
			}
		},
		{
			"scope": "markup.underline, markup.underline.link.markdown",
			"settings": {
				"foreground": "#00d3ffc8"
			}
		},
		{
			"scope": "markup.bold",
			"settings": {
				"foreground": "#a3c3ffc8",
			}
		},
		{
			"scope": "markup.italic",
			"settings": {
				"foreground": "#a3c3ffc8",
			}
		},
		{
			"scope": "markup.strikethrough",
			"settings": {
				"fontStyle": "strikethrough"
			}
		},
		{
			"scope": "markup.inline.raw",
			"settings": {
				"foreground": "#ffbc7fc8",
				"fontStyle": ""
			}
		},
		{
			"scope": "heading.1.markdown entity.name.section.markdown",
			"settings": {
				"foreground": "#00a3ffc8"
			}
		},
		{
			"scope": "heading.2.markdown entity.name.section.markdown",
			"settings": {
				"foreground": "#00a3ffc8"
			}
		},
		{
			"scope": "heading.3.markdown entity.name.section.markdown",
			"settings": {
				"foreground": "#00a3ffc8"
			}
		},
		{
			"scope": "heading.4.markdown entity.name.section.markdown",
			"settings": {
				"foreground": "#00a3ffc8"
			}
		},
		{
			"scope": "heading.5.markdown entity.name.section.markdown",
			"settings": {
				"foreground": "#00a3ffc8"
			}
		},
		{
			"scope": "heading.6.markdown entity.name.section.markdown",
			"settings": {
				"foreground": "#00a3ffc8"
			}
		},
		{
			"scope": "meta.diff.header.from-file, meta.diff.header.to-file",
			"settings": {
				"foreground": "#4872F1c8"
			}
		},
		{
			"scope": "meta.diff.range",
			"settings": {
				"foreground": "#123c78c8",
				"fontStyle": "italic"
			}
		},
		{
			"scope": "markup.deleted.diff, meta.diff.header.from-file",
			"settings": {
				"foreground": "#C82828c8",
				"fontStyle": ""
			}
		},
		{
			"scope": "markup.inserted.diff, markup.deleted.diff, meta.diff.header.to-file, meta.diff.header.from-file",
			"settings": {
				"foreground": "#FFFFFFc8",
				"fontStyle": ""
			}
		},
		{
			"scope": "markup.inserted.diff, meta.diff.header.to-file",
			"settings": {
				"foreground": "#7fc300c8",
				"fontStyle": ""
			}
		},
		{
			"scope": "constant.other",
			"settings": {
				"foreground": "#d8a3ffc8"
			}
		},
		{
			"scope": "entity.other.attribute-name.pseudo-class.css, entity.other.attribute-name.pseudo-element.css",
			"settings": {
				"foreground": "#00a3FFc8"
			}
		},
		{
			"scope": "entity.other.attribute-name.id.css",
			"settings": {
				"foreground": "#f1a388c8"
			}
		},
		{
			"scope": "entity.other.attribute-name.class.css",
			"settings": {
				"foreground": "#d8d8d8c8"
			}
		},
		{
			"scope": "string.quoted.docstring.multi.python",
			"settings": {
				"foreground": "#787878c8",
				"fontStyle": "italic"
			}
		},
		{
			"scope": "support.type.property-name, support.type.vendored.property-name.css",
			"settings": {
				"foreground": "#308ddfc8"
			}
		},
		{
			"scope": "keyword.other.important.css",
			"settings": {
				"foreground": "#f100f1c8",
				"fontStyle": ""
			}
		},
		{
			"scope": "variable.css,variable.argument.css",
			"settings": {
				"foreground": "#f18282c8",
				"fontStyle": ""
			}
		},
		{
			"scope": "variable.parameter.keyframe-list.css",
			"settings": {
				"foreground": "#00c8c8c8",
				"fontStyle": "bold"
			}
		},
		{
			"scope": "punctuation.accessor.js,punctuation.definition.section.case-statement.js",
			"settings": {
				"foreground": "#d372ffc8",
				"fontStyle": "bold"
			}
		},
		{
			"scope": "punctuation.support.type.property-name.begin.json,punctuation.support.type.property-name.end.json",
			"settings": {
				"foreground": "#00d8ffc8"
			}
		},
		{
			"scope": "punctuation.section.embedded.begin.php, punctuation.section.embedded.end.php,",
			"settings": {
				"foreground": "#FF8800c8",
				"fontStyle": "bold"
			}
		},
		{
			"scope": "variable.other.global.php, variable.other.global.safer.php",
			"settings": {
				"foreground": "#00C3FFc8",
				"fontStyle": "bold"
			}
		},
		{
			"scope": "entity.name.function, meta.function-call, support.function, keyword.other.special-method, meta.block-level, markup.changed.git_gutter",
			"settings": {
				"foreground": "#48f148c8"
			}
		},
		{
			"scope": "keyword,keyword.control, storage, storage.type, entity.name.tag.css, entity.other.inherited-class",
			"settings": {
				"foreground": "#d372ffc8",
				"fontStyle": ""
			}
		},
		{
			"scope": "invalid",
			"settings": {
				"foreground": "#F12048c8",
				"fontStyle": ""
			}
		},
		{
			"scope": "meta.separator, meta.function-call.c",
			"settings": {
				"foreground": "#d8d8d8c8"
			}
		},
		{
			"scope": "invalid.deprecated",
			"settings": {
				"foreground": "#FFF128c8",
				"fontStyle": "bold underline"
			}
		},
		{
			"name": "Regular Expressions",
			"scope": [
				"string.regexp"
			],
			"settings": {
				"foreground": "#cbff88c8"
			}
		},
		{
			"name": "Escape Characters",
			"scope": [
				"constant.character.escape"
			],
			"settings": {
				"foreground": "#b9c455c8"
			}
		},
		{
			"name": "URL",
			"scope": [
				"*url*",
				"*link*",
				"*uri*"
			],
			"settings": {
				"fontStyle": "underline"
			}
		},
		{
			"name": "JSON Key - Level 0",
			"scope": [
				"source.json meta.structure.dictionary.json support.type.property-name.json"
			],
			"settings": {
				"foreground": "#d8d8d8c8"
			}
		},
		{
			"name": "JSON Key - Level 1",
			"scope": [
				"source.json meta.structure.dictionary.json meta.structure.dictionary.value.json meta.structure.dictionary.json support.type.property-name.json"
			],
			"settings": {
				"foreground": "#f1a3ffc8"
			}
		},
		{
			"name": "JSON Key - Level 2",
			"scope": [
				"source.json meta.structure.dictionary.json meta.structure.dictionary.value.json meta.structure.dictionary.json meta.structure.dictionary.value.json meta.structure.dictionary.json support.type.property-name.json"
			],
			"settings": {
				"foreground": "#ffa348c8"
			}
		},
		{
			"name": "JSON Key - Level 3",
			"scope": [
				"source.json meta.structure.dictionary.json meta.structure.dictionary.value.json meta.structure.dictionary.json meta.structure.dictionary.value.json meta.structure.dictionary.json meta.structure.dictionary.value.json meta.structure.dictionary.json support.type.property-name.json"
			],
			"settings": {
				"foreground": "#FFd372c8"
			}
		},
		{
			"name": "JSON Key - Level 4",
			"scope": [
				"source.json meta.structure.dictionary.json meta.structure.dictionary.value.json meta.structure.dictionary.json meta.structure.dictionary.value.json meta.structure.dictionary.json meta.structure.dictionary.value.json meta.structure.dictionary.json meta.structure.dictionary.value.json meta.structure.dictionary.json support.type.property-name.json"
			],
			"settings": {
				"foreground": "#f1f188c8"
			}
		},
		{
			"name": "JSON Key - Level 5",
			"scope": [
				"source.json meta.structure.dictionary.json meta.structure.dictionary.value.json meta.structure.dictionary.json meta.structure.dictionary.value.json meta.structure.dictionary.json meta.structure.dictionary.value.json meta.structure.dictionary.json meta.structure.dictionary.value.json meta.structure.dictionary.json meta.structure.dictionary.value.json meta.structure.dictionary.json support.type.property-name.json"
			],
			"settings": {
				"foreground": "#a3A3FFc8"
			}
		},
		{
			"name": "JSON Key - Level 6",
			"scope": [
				"source.json meta.structure.dictionary.json meta.structure.dictionary.value.json meta.structure.dictionary.json meta.structure.dictionary.value.json meta.structure.dictionary.json meta.structure.dictionary.value.json meta.structure.dictionary.json meta.structure.dictionary.value.json meta.structure.dictionary.json meta.structure.dictionary.value.json meta.structure.dictionary.json meta.structure.dictionary.value.json meta.structure.dictionary.json support.type.property-name.json"
			],
			"settings": {
				"foreground": "#78ff78c8"
			}
		},
		{
			"name": "JSON Key - Level 7",
			"scope": [
				"source.json meta.structure.dictionary.json meta.structure.dictionary.value.json meta.structure.dictionary.json meta.structure.dictionary.value.json meta.structure.dictionary.json meta.structure.dictionary.value.json meta.structure.dictionary.json meta.structure.dictionary.value.json meta.structure.dictionary.json meta.structure.dictionary.value.json meta.structure.dictionary.json meta.structure.dictionary.value.json meta.structure.dictionary.json meta.structure.dictionary.value.json meta.structure.dictionary.json support.type.property-name.json"
			],
			"settings": {
				"foreground": "#48d3d3c8"
			}
		},
		{
			"name": "JSON Key - Level 8",
			"scope": [
				"source.json meta.structure.dictionary.json meta.structure.dictionary.value.json meta.structure.dictionary.json meta.structure.dictionary.value.json meta.structure.dictionary.json meta.structure.dictionary.value.json meta.structure.dictionary.json meta.structure.dictionary.value.json meta.structure.dictionary.json meta.structure.dictionary.value.json meta.structure.dictionary.json meta.structure.dictionary.value.json meta.structure.dictionary.json meta.structure.dictionary.value.json meta.structure.dictionary.json meta.structure.dictionary.value.json meta.structure.dictionary.json support.type.property-name.json"
			],
			"settings": {
				"foreground": "#f1f1f1c8"
			}
		},
		{
			"scope": "entity.other.attribute-name",
			"settings": {
				"foreground": "#ffa3a3c8",
				"fontStyle": ""
			}
		},
		{
			"scope": "meta.at-rule.header.css",
			"settings": {
				"foreground": "#00f1f1c8",
				"fontStyle": ""
			}
		},
		{
			"scope": "keyword.other.unit",
			"settings": {
				"foreground": "#00a3a3c8",
				"fontStyle": ""
			}
		},
		{
			"scope": "entity.other.inherited-class.ruby",
			"settings": {
				"foreground": "#f18800c8",
				"fontStyle": "italic"
			}
		},
		{
			"scope": "variable.scss, meta.definition.variable.scss",
			"settings": {
				"foreground": "#f18282c8",
				"fontStyle": ""
			}
		},
		{
			"scope": "entity.other.attribute-name.placeholder.css",
			"settings": {
				"foreground": "#b3b300c8",
				"fontStyle": "bold"
			}
		},
		{
			"scope": [
				"keyword.operator.new",
				"keyword.operator.expression",
				"keyword.operator.cast",
				"keyword.operator.sizeof",
				"keyword.operator.alignof",
				"keyword.operator.typeid",
				"keyword.operator.alignas",
				"keyword.operator.instanceof",
				"keyword.operator.logical.python",
				"keyword.operator.wordlike"
			],
			"settings": {
				"foreground": "#c300f1c8"
			}
		},
		{
			"scope": [
				"keyword.control.import.include.php",
				"meta.include.php",
				"meta.embedded.line.php",
				"text.html.php",
			],
			"settings": {
				"foreground": "#48f148c8"
			}
		},
		{
			"scope": [
				"variable.other.object.js",
				"meta.function-call.js",
				"meta.object.member.js",
				"meta.objectliteral.js",
				"meta.var.expr.js"
			],
			"settings": {
				"foreground": "#7373ffc8",
				"fontStyle": ""
			}
		},
		{
			"scope": [
				"meta.object-literal.key.js",
				"meta.object.member.js",
				"meta.objectliteral.js",
				"meta.var.expr.js"
			],
			"settings": {
				"foreground": "#9aaccec8",
				"fontStyle": ""
			}
		},
		{
			"scope": "variable.language.this.php, punctuation.definition.variable.php",
			"settings": {
				"foreground": "#0088f1c8",
				"fontStyle": ""
			}
		},
		{
			"scope": "keyword.operator.class.php",
			"settings": {
				"foreground": "#d372ffc8",
				"fontStyle": ""
			}
		}
	]
}